tourbillon_elasticsearch-0.4.2-py2.7-nspkg.pth
tourbillon/elasticsearch/__init__.py
tourbillon/elasticsearch/elasticsearch/__init__.py
tourbillon/elasticsearch/elasticsearch/elasticsearch.py
tourbillon/elasticsearch/elasticsearch2/__init__.py
tourbillon/elasticsearch/elasticsearch2/elasticsearch.py
tourbillon_elasticsearch-0.4.2.dist-info/DESCRIPTION.rst
tourbillon_elasticsearch-0.4.2.dist-info/METADATA
tourbillon_elasticsearch-0.4.2.dist-info/RECORD
tourbillon_elasticsearch-0.4.2.dist-info/WHEEL
tourbillon_elasticsearch-0.4.2.dist-info/metadata.json
tourbillon_elasticsearch-0.4.2.dist-info/namespace_packages.txt
tourbillon_elasticsearch-0.4.2.dist-info/top_level.txt
